{"assets/images/%C3%84.png":["assets/images/%C3%84.png"],"assets/images/%C3%96.png":["assets/images/%C3%96.png"],"assets/images/%C3%9C.png":["assets/images/%C3%9C.png"],"assets/images/%C3%9F.png":["assets/images/%C3%9F.png"],"assets/images/1.png":["assets/images/1.png"],"assets/images/10.png":["assets/images/10.png"],"assets/images/100.png":["assets/images/100.png"],"assets/images/1000.png":["assets/images/1000.png"],"assets/images/11.png":["assets/images/11.png"],"assets/images/13.png":["assets/images/13.png"],"assets/images/14.png":["assets/images/14.png"],"assets/images/15.png":["assets/images/15.png"],"assets/images/16.png":["assets/images/16.png"],"assets/images/2.png":["assets/images/2.png"],"assets/images/20.png":["assets/images/20.png"],"assets/images/200.png":["assets/images/200.png"],"assets/images/2000.png":["assets/images/2000.png"],"assets/images/21.png":["assets/images/21.png"],"assets/images/22.png":["assets/images/22.png"],"assets/images/24.png":["assets/images/24.png"],"assets/images/24a.png":["assets/images/24a.png"],"assets/images/3.png":["assets/images/3.png"],"assets/images/30.png":["assets/images/30.png"],"assets/images/33.png":["assets/images/33.png"],"assets/images/4.png":["assets/images/4.png"],"assets/images/40.png":["assets/images/40.png"],"assets/images/5.png":["assets/images/5.png"],"assets/images/50.png":["assets/images/50.png"],"assets/images/6.png":["assets/images/6.png"],"assets/images/60.png":["assets/images/60.png"],"assets/images/7.png":["assets/images/7.png"],"assets/images/8.png":["assets/images/8.png"],"assets/images/9.png":["assets/images/9.png"],"assets/images/A.png":["assets/images/A.png"],"assets/images/B.png":["assets/images/B.png"],"assets/images/Baby.png":["assets/images/Baby.png"],"assets/images/Bruder.png":["assets/images/Bruder.png"],"assets/images/C.png":["assets/images/C.png"],"assets/images/D.png":["assets/images/D.png"],"assets/images/E.png":["assets/images/E.png"],"assets/images/Einkaufswagen.png":["assets/images/Einkaufswagen.png"],"assets/images/Euro.png":["assets/images/Euro.png"],"assets/images/F.png":["assets/images/F.png"],"assets/images/G.png":["assets/images/G.png"],"assets/images/Geld.png":["assets/images/Geld.png"],"assets/images/Gesch%C3%A4ft.png":["assets/images/Gesch%C3%A4ft.png"],"assets/images/Gro%C3%9Feltern.png":["assets/images/Gro%C3%9Feltern.png"],"assets/images/H.png":["assets/images/H.png"],"assets/images/Halbschwester.png":["assets/images/Halbschwester.png"],"assets/images/I.png":["assets/images/I.png"],"assets/images/J.png":["assets/images/J.png"],"assets/images/K.png":["assets/images/K.png"],"assets/images/Kasse.png":["assets/images/Kasse.png"],"assets/images/Kind.png":["assets/images/Kind.png"],"assets/images/Kinder.png":["assets/images/Kinder.png"],"assets/images/Kunde.png":["assets/images/Kunde.png"],"assets/images/L.png":["assets/images/L.png"],"assets/images/Laden.png":["assets/images/Laden.png"],"assets/images/Lebensmittel.png":["assets/images/Lebensmittel.png"],"assets/images/M.png":["assets/images/M.png"],"assets/images/Mama.png":["assets/images/Mama.png"],"assets/images/Markt.png":["assets/images/Markt.png"],"assets/images/N.png":["assets/images/N.png"],"assets/images/O.png":["assets/images/O.png"],"assets/images/Opa.png":["assets/images/Opa.png"],"assets/images/P.png":["assets/images/P.png"],"assets/images/Papa.png":["assets/images/Papa.png"],"assets/images/Preis.png":["assets/images/Preis.png"],"assets/images/Q.png":["assets/images/Q.png"],"assets/images/R.png":["assets/images/R.png"],"assets/images/Rechnung.png":["assets/images/Rechnung.png"],"assets/images/S.png":["assets/images/S.png"],"assets/images/Sohn.png":["assets/images/Sohn.png"],"assets/images/Stiefbruder.png":["assets/images/Stiefbruder.png"],"assets/images/T.png":["assets/images/T.png"],"assets/images/U.png":["assets/images/U.png"],"assets/images/V.png":["assets/images/V.png"],"assets/images/W.png":["assets/images/W.png"],"assets/images/X.png":["assets/images/X.png"],"assets/images/Y.png":["assets/images/Y.png"],"assets/images/Z.png":["assets/images/Z.png"],"assets/images/Zwilling.png":["assets/images/Zwilling.png"],"assets/images/abcd.jpg":["assets/images/abcd.jpg"],"assets/images/beruehren_schrift.jpg":["assets/images/beruehren_schrift.jpg"],"assets/images/beruehren_symbol.jpg":["assets/images/beruehren_symbol.jpg"],"assets/images/bervideobild.jpg":["assets/images/bervideobild.jpg"],"assets/images/dumm.png":["assets/images/dumm.png"],"assets/images/ehrlich.png":["assets/images/ehrlich.png"],"assets/images/eifers%C3%BCchtig.png":["assets/images/eifers%C3%BCchtig.png"],"assets/images/empfindlich.png":["assets/images/empfindlich.png"],"assets/images/f5h.jpg":["assets/images/f5h.jpg"],"assets/images/faul.png":["assets/images/faul.png"],"assets/images/flei%C3%9Fig.png":["assets/images/flei%C3%9Fig.png"],"assets/images/fr%C3%B6hlich.png":["assets/images/fr%C3%B6hlich.png"],"assets/images/frech.png":["assets/images/frech.png"],"assets/images/freundlich.png":["assets/images/freundlich.png"],"assets/images/fzh_bild.jpg":["assets/images/fzh_bild.jpg"],"assets/images/fzh_schrift.jpg":["assets/images/fzh_schrift.jpg"],"assets/images/fzh_symbol.jpg":["assets/images/fzh_symbol.jpg"],"assets/images/geduldig.png":["assets/images/geduldig.png"],"assets/images/gl%C3%BCcklich.png":["assets/images/gl%C3%BCcklich.png"],"assets/images/greifen_schrift.jpg":["assets/images/greifen_schrift.jpg"],"assets/images/greifen_symbol.jpg":["assets/images/greifen_symbol.jpg"],"assets/images/greifenvideobild.jpg":["assets/images/greifenvideobild.jpg"],"assets/images/gzh_bild.jpg":["assets/images/gzh_bild.jpg"],"assets/images/gzh_schrift.jpg":["assets/images/gzh_schrift.jpg"],"assets/images/gzh_symbol.jpg":["assets/images/gzh_symbol.jpg"],"assets/images/handflaeche_schrift.jpg":["assets/images/handflaeche_schrift.jpg"],"assets/images/handkante_bild.jpg":["assets/images/handkante_bild.jpg"],"assets/images/handkante_schrift.jpg":["assets/images/handkante_schrift.jpg"],"assets/images/handkante_symbol.jpg":["assets/images/handkante_symbol.jpg"],"assets/images/handruecken_bild.jpg":["assets/images/handruecken_bild.jpg"],"assets/images/handruecken_schrift.jpg":["assets/images/handruecken_schrift.jpg"],"assets/images/handruecken_symbol.jpg":["assets/images/handruecken_symbol.jpg"],"assets/images/hk_image101.jpg":["assets/images/hk_image101.jpg"],"assets/images/hk_image102.jpg":["assets/images/hk_image102.jpg"],"assets/images/hk_image103.jpg":["assets/images/hk_image103.jpg"],"assets/images/hk_image201.jpg":["assets/images/hk_image201.jpg"],"assets/images/hk_image202.jpg":["assets/images/hk_image202.jpg"],"assets/images/hk_image203.jpg":["assets/images/hk_image203.jpg"],"assets/images/hk_image301.jpg":["assets/images/hk_image301.jpg"],"assets/images/hk_image302.jpg":["assets/images/hk_image302.jpg"],"assets/images/hk_image303.jpg":["assets/images/hk_image303.jpg"],"assets/images/ic_image101.jpg":["assets/images/ic_image101.jpg"],"assets/images/ic_image102.jpg":["assets/images/ic_image102.jpg"],"assets/images/ic_image103.jpg":["assets/images/ic_image103.jpg"],"assets/images/ic_image201.jpg":["assets/images/ic_image201.jpg"],"assets/images/ic_image202.jpg":["assets/images/ic_image202.jpg"],"assets/images/ic_image203.jpg":["assets/images/ic_image203.jpg"],"assets/images/ic_image301.jpg":["assets/images/ic_image301.jpg"],"assets/images/ic_image302.jpg":["assets/images/ic_image302.jpg"],"assets/images/ic_image303.jpg":["assets/images/ic_image303.jpg"],"assets/images/if_image101.jpg":["assets/images/if_image101.jpg"],"assets/images/if_image102.jpg":["assets/images/if_image102.jpg"],"assets/images/if_image103.jpg":["assets/images/if_image103.jpg"],"assets/images/if_image201.jpg":["assets/images/if_image201.jpg"],"assets/images/if_image202.jpg":["assets/images/if_image202.jpg"],"assets/images/if_image203.jpg":["assets/images/if_image203.jpg"],"assets/images/if_image301.jpg":["assets/images/if_image301.jpg"],"assets/images/if_image302.jpg":["assets/images/if_image302.jpg"],"assets/images/if_image303.jpg":["assets/images/if_image303.jpg"],"assets/images/ig1_image101.jpg":["assets/images/ig1_image101.jpg"],"assets/images/ig1_image102.jpg":["assets/images/ig1_image102.jpg"],"assets/images/ig1_image103.jpg":["assets/images/ig1_image103.jpg"],"assets/images/ig1_image201.jpg":["assets/images/ig1_image201.jpg"],"assets/images/ig1_image202.jpg":["assets/images/ig1_image202.jpg"],"assets/images/ig1_image203.jpg":["assets/images/ig1_image203.jpg"],"assets/images/ig1_image301.jpg":["assets/images/ig1_image301.jpg"],"assets/images/ig1_image302.jpg":["assets/images/ig1_image302.jpg"],"assets/images/ig1_image303.jpg":["assets/images/ig1_image303.jpg"],"assets/images/ig2_image101.jpg":["assets/images/ig2_image101.jpg"],"assets/images/ig2_image102.jpg":["assets/images/ig2_image102.jpg"],"assets/images/ig2_image103.jpg":["assets/images/ig2_image103.jpg"],"assets/images/ig2_image201.jpg":["assets/images/ig2_image201.jpg"],"assets/images/ig2_image202.jpg":["assets/images/ig2_image202.jpg"],"assets/images/ig2_image203.jpg":["assets/images/ig2_image203.jpg"],"assets/images/ig2_image301.jpg":["assets/images/ig2_image301.jpg"],"assets/images/ig2_image302.jpg":["assets/images/ig2_image302.jpg"],"assets/images/ig2_image303.jpg":["assets/images/ig2_image303.jpg"],"assets/images/klug.png":["assets/images/klug.png"],"assets/images/lieb.png":["assets/images/lieb.png"],"assets/images/nerv%C3%B6s.png":["assets/images/nerv%C3%B6s.png"],"assets/images/neugierig.png":["assets/images/neugierig.png"],"assets/images/niedlich.png":["assets/images/niedlich.png"],"assets/images/of1_image101.jpg":["assets/images/of1_image101.jpg"],"assets/images/of1_image102.jpg":["assets/images/of1_image102.jpg"],"assets/images/of1_image103.jpg":["assets/images/of1_image103.jpg"],"assets/images/of1_image201.jpg":["assets/images/of1_image201.jpg"],"assets/images/of1_image202.jpg":["assets/images/of1_image202.jpg"],"assets/images/of1_image203.jpg":["assets/images/of1_image203.jpg"],"assets/images/of1_image301.jpg":["assets/images/of1_image301.jpg"],"assets/images/of1_image302.jpg":["assets/images/of1_image302.jpg"],"assets/images/of1_image303.jpg":["assets/images/of1_image303.jpg"],"assets/images/of2_image101.jpg":["assets/images/of2_image101.jpg"],"assets/images/of2_image102.jpg":["assets/images/of2_image102.jpg"],"assets/images/of2_image103.jpg":["assets/images/of2_image103.jpg"],"assets/images/of2_image201.jpg":["assets/images/of2_image201.jpg"],"assets/images/of2_image202.jpg":["assets/images/of2_image202.jpg"],"assets/images/of2_image203.jpg":["assets/images/of2_image203.jpg"],"assets/images/of2_image301.jpg":["assets/images/of2_image301.jpg"],"assets/images/of2_image302.jpg":["assets/images/of2_image302.jpg"],"assets/images/of2_image303.jpg":["assets/images/of2_image303.jpg"],"assets/images/ozh_bild.jpg":["assets/images/ozh_bild.jpg"],"assets/images/ozh_schrift.jpg":["assets/images/ozh_schrift.jpg"],"assets/images/ozh_symbol.jpg":["assets/images/ozh_symbol.jpg"],"assets/images/peinlich.png":["assets/images/peinlich.png"],"assets/images/punkte.jpg":["assets/images/punkte.jpg"],"assets/images/reiben_schrift.jpg":["assets/images/reiben_schrift.jpg"],"assets/images/reiben_symbol.jpg":["assets/images/reiben_symbol.jpg"],"assets/images/reibenvideobild.jpg":["assets/images/reibenvideobild.jpg"],"assets/images/sch%C3%BCchtern.png":["assets/images/sch%C3%BCchtern.png"],"assets/images/stolz.png":["assets/images/stolz.png"],"assets/images/stur.png":["assets/images/stur.png"],"assets/images/verliebt.png":["assets/images/verliebt.png"],"assets/images/zahlen.jpg":["assets/images/zahlen.jpg"],"assets/videos/%C3%9F.mp4":["assets/videos/%C3%9F.mp4"],"assets/videos/%C3%A4.mp4":["assets/videos/%C3%A4.mp4"],"assets/videos/%C3%B6.mp4":["assets/videos/%C3%B6.mp4"],"assets/videos/%C3%BC.mp4":["assets/videos/%C3%BC.mp4"],"assets/videos/1.452.345.mp4":["assets/videos/1.452.345.mp4"],"assets/videos/1.mp4":["assets/videos/1.mp4"],"assets/videos/10.mp4":["assets/videos/10.mp4"],"assets/videos/100.mp4":["assets/videos/100.mp4"],"assets/videos/1000.mp4":["assets/videos/1000.mp4"],"assets/videos/11.mp4":["assets/videos/11.mp4"],"assets/videos/12.mp4":["assets/videos/12.mp4"],"assets/videos/13.mp4":["assets/videos/13.mp4"],"assets/videos/14.mp4":["assets/videos/14.mp4"],"assets/videos/15.mp4":["assets/videos/15.mp4"],"assets/videos/16.mp4":["assets/videos/16.mp4"],"assets/videos/2.mp4":["assets/videos/2.mp4"],"assets/videos/20.mp4":["assets/videos/20.mp4"],"assets/videos/200.mp4":["assets/videos/200.mp4"],"assets/videos/2000.mp4":["assets/videos/2000.mp4"],"assets/videos/21.mp4":["assets/videos/21.mp4"],"assets/videos/22.mp4":["assets/videos/22.mp4"],"assets/videos/24.mp4":["assets/videos/24.mp4"],"assets/videos/3.mp4":["assets/videos/3.mp4"],"assets/videos/30.mp4":["assets/videos/30.mp4"],"assets/videos/33.mp4":["assets/videos/33.mp4"],"assets/videos/4.mp4":["assets/videos/4.mp4"],"assets/videos/40.mp4":["assets/videos/40.mp4"],"assets/videos/5.mp4":["assets/videos/5.mp4"],"assets/videos/50.mp4":["assets/videos/50.mp4"],"assets/videos/6.mp4":["assets/videos/6.mp4"],"assets/videos/60.mp4":["assets/videos/60.mp4"],"assets/videos/7.mp4":["assets/videos/7.mp4"],"assets/videos/8.mp4":["assets/videos/8.mp4"],"assets/videos/9.mp4":["assets/videos/9.mp4"],"assets/videos/A-37.m4v":["assets/videos/A-37.m4v"],"assets/videos/Bruder.mp4":["assets/videos/Bruder.mp4"],"assets/videos/Gesch%C3%A4ft.mp4":["assets/videos/Gesch%C3%A4ft.mp4"],"assets/videos/Laden.mp4":["assets/videos/Laden.mp4"],"assets/videos/Markt.mp4":["assets/videos/Markt.mp4"],"assets/videos/Preis.mp4":["assets/videos/Preis.mp4"],"assets/videos/Rechnung.mp4":["assets/videos/Rechnung.mp4"],"assets/videos/a.m4v":["assets/videos/a.m4v"],"assets/videos/a.mp4":["assets/videos/a.mp4"],"assets/videos/aldi.mp4":["assets/videos/aldi.mp4"],"assets/videos/auto.mp4":["assets/videos/auto.mp4"],"assets/videos/autogif.mp4":["assets/videos/autogif.mp4"],"assets/videos/b.mp4":["assets/videos/b.mp4"],"assets/videos/baby.mp4":["assets/videos/baby.mp4"],"assets/videos/baum.mp4":["assets/videos/baum.mp4"],"assets/videos/baumgif.mp4":["assets/videos/baumgif.mp4"],"assets/videos/c.mp4":["assets/videos/c.mp4"],"assets/videos/cent.mp4":["assets/videos/cent.mp4"],"assets/videos/d.mp4":["assets/videos/d.mp4"],"assets/videos/deprimiert.mp4":["assets/videos/deprimiert.mp4"],"assets/videos/dumm.mp4":["assets/videos/dumm.mp4"],"assets/videos/e.mp4":["assets/videos/e.mp4"],"assets/videos/ehrlich.mp4":["assets/videos/ehrlich.mp4"],"assets/videos/eifers%C3%BCchtig.mp4":["assets/videos/eifers%C3%BCchtig.mp4"],"assets/videos/einkaufswagen.mp4":["assets/videos/einkaufswagen.mp4"],"assets/videos/einzelkind.mp4":["assets/videos/einzelkind.mp4"],"assets/videos/eltern.mp4":["assets/videos/eltern.mp4"],"assets/videos/empfindlich.mp4":["assets/videos/empfindlich.mp4"],"assets/videos/enkel.mp4":["assets/videos/enkel.mp4"],"assets/videos/euro.mp4":["assets/videos/euro.mp4"],"assets/videos/f.mp4":["assets/videos/f.mp4"],"assets/videos/familie.mp4":["assets/videos/familie.mp4"],"assets/videos/faul.mp4":["assets/videos/faul.mp4"],"assets/videos/flei%C3%9Fig.mp4":["assets/videos/flei%C3%9Fig.mp4"],"assets/videos/fr%C3%B6hlich.mp4":["assets/videos/fr%C3%B6hlich.mp4"],"assets/videos/frech.mp4":["assets/videos/frech.mp4"],"assets/videos/freundlich.mp4":["assets/videos/freundlich.mp4"],"assets/videos/g.mp4":["assets/videos/g.mp4"],"assets/videos/geduldig.mp4":["assets/videos/geduldig.mp4"],"assets/videos/geld.mp4":["assets/videos/geld.mp4"],"assets/videos/gemein.mp4":["assets/videos/gemein.mp4"],"assets/videos/geschwister.mp4":["assets/videos/geschwister.mp4"],"assets/videos/gl%C3%BCcklich.mp4":["assets/videos/gl%C3%BCcklich.mp4"],"assets/videos/h.mp4":["assets/videos/h.mp4"],"assets/videos/halbschwester.mp4":["assets/videos/halbschwester.mp4"],"assets/videos/i.mp4":["assets/videos/i.mp4"],"assets/videos/j.mp4":["assets/videos/j.mp4"],"assets/videos/k.mp4":["assets/videos/k.mp4"],"assets/videos/kaffee.mp4":["assets/videos/kaffee.mp4"],"assets/videos/kaffeegif.mp4":["assets/videos/kaffeegif.mp4"],"assets/videos/kasse.mp4":["assets/videos/kasse.mp4"],"assets/videos/kind.mp4":["assets/videos/kind.mp4"],"assets/videos/kinder.mp4":["assets/videos/kinder.mp4"],"assets/videos/klug.mp4":["assets/videos/klug.mp4"],"assets/videos/kunde.mp4":["assets/videos/kunde.mp4"],"assets/videos/l.mp4":["assets/videos/l.mp4"],"assets/videos/lebensmittel.mp4":["assets/videos/lebensmittel.mp4"],"assets/videos/lidl.mp4":["assets/videos/lidl.mp4"],"assets/videos/lieb.mp4":["assets/videos/lieb.mp4"],"assets/videos/m.mp4":["assets/videos/m.mp4"],"assets/videos/mama.mp4":["assets/videos/mama.mp4"],"assets/videos/muenze.mp4":["assets/videos/muenze.mp4"],"assets/videos/n.mp4":["assets/videos/n.mp4"],"assets/videos/naiv.mp4":["assets/videos/naiv.mp4"],"assets/videos/nervoes.mp4":["assets/videos/nervoes.mp4"],"assets/videos/neugierig.mp4":["assets/videos/neugierig.mp4"],"assets/videos/niedlich.mp4":["assets/videos/niedlich.mp4"],"assets/videos/o.mp4":["assets/videos/o.mp4"],"assets/videos/onkel.mp4":["assets/videos/onkel.mp4"],"assets/videos/p.mp4":["assets/videos/p.mp4"],"assets/videos/papa.mp4":["assets/videos/papa.mp4"],"assets/videos/peinlich.mp4":["assets/videos/peinlich.mp4"],"assets/videos/q.mp4":["assets/videos/q.mp4"],"assets/videos/r.mp4":["assets/videos/r.mp4"],"assets/videos/rechnungsbeleg.mp4":["assets/videos/rechnungsbeleg.mp4"],"assets/videos/s.mp4":["assets/videos/s.mp4"],"assets/videos/sch%C3%BCchtern.mp4":["assets/videos/sch%C3%BCchtern.mp4"],"assets/videos/sohn.mp4":["assets/videos/sohn.mp4"],"assets/videos/stiefbruder.mp4":["assets/videos/stiefbruder.mp4"],"assets/videos/stolz.mp4":["assets/videos/stolz.mp4"],"assets/videos/stur.mp4":["assets/videos/stur.mp4"],"assets/videos/supermarkt.mp4":["assets/videos/supermarkt.mp4"],"assets/videos/t.mp4":["assets/videos/t.mp4"],"assets/videos/u.mp4":["assets/videos/u.mp4"],"assets/videos/v.mp4":["assets/videos/v.mp4"],"assets/videos/verliebt.mp4":["assets/videos/verliebt.mp4"],"assets/videos/w.mp4":["assets/videos/w.mp4"],"assets/videos/waren.mp4":["assets/videos/waren.mp4"],"assets/videos/x.mp4":["assets/videos/x.mp4"],"assets/videos/y.mp4":["assets/videos/y.mp4"],"assets/videos/z.mp4":["assets/videos/z.mp4"],"assets/videos/zufrieden.mp4":["assets/videos/zufrieden.mp4"],"packages/cupertino_icons/assets/CupertinoIcons.ttf":["packages/cupertino_icons/assets/CupertinoIcons.ttf"]}